yanex/__init__.py
yanex/api.py
yanex/executor.py
yanex/cli/__init__.py
yanex/cli/_utils.py
yanex/cli/error_handling.py
yanex/cli/main.py
yanex/cli/commands/__init__.py
yanex/cli/commands/archive.py
yanex/cli/commands/compare.py
yanex/cli/commands/confirm.py
yanex/cli/commands/delete.py
yanex/cli/commands/get.py
yanex/cli/commands/list.py
yanex/cli/commands/migrate.py
yanex/cli/commands/open.py
yanex/cli/commands/run.py
yanex/cli/commands/show.py
yanex/cli/commands/ui.py
yanex/cli/commands/unarchive.py
yanex/cli/commands/update.py
yanex/cli/filters/__init__.py
yanex/cli/filters/arguments.py
yanex/cli/filters/time_utils.py
yanex/cli/formatters/__init__.py
yanex/cli/formatters/console.py
yanex/cli/formatters/csv_formatter.py
yanex/cli/formatters/fields.py
yanex/cli/formatters/getter_output.py
yanex/cli/formatters/json_formatter.py
yanex/cli/formatters/lineage.py
yanex/cli/formatters/markdown_formatter.py
yanex/cli/formatters/output.py
yanex/cli/formatters/serializers.py
yanex/cli/formatters/theme.py
yanex/core/__init__.py
yanex/core/artifact_formats.py
yanex/core/artifact_io.py
yanex/core/comparison.py
yanex/core/config.py
yanex/core/constants.py
yanex/core/dependencies.py
yanex/core/dependency_graph.py
yanex/core/environment.py
yanex/core/filtering.py
yanex/core/git_utils.py
yanex/core/manager.py
yanex/core/migrations.py
yanex/core/param_tracking.py
yanex/core/parameter_parser_factory.py
yanex/core/parameter_parsers.py
yanex/core/script_executor.py
yanex/core/storage.py
yanex/core/storage_archive.py
yanex/core/storage_artifacts.py
yanex/core/storage_composition.py
yanex/core/storage_config.py
yanex/core/storage_directory.py
yanex/core/storage_executions.py
yanex/core/storage_interfaces.py
yanex/core/storage_metadata.py
yanex/core/storage_metrics.py
yanex/core/tracked_dict.py
yanex/results/__init__.py
yanex/results/dataframe.py
yanex/results/experiment.py
yanex/results/manager.py
yanex/ui/__init__.py
yanex/ui/compare_table.py
yanex/utils/__init__.py
yanex-0.5.0.dist-info/licenses/LICENSE
yanex-0.5.0.dist-info/METADATA
yanex-0.5.0.dist-info/WHEEL
yanex-0.5.0.dist-info/entry_points.txt
yanex-0.5.0.dist-info/top_level.txt
yanex-0.5.0.dist-info/RECORD
