Metadata-Version: 2.4
Name: yanex
Version: 0.5.0
Summary: Yet Another Experiment Tracker - A lightweight experiment tracking harness
Author: Thomas
Author-email: Thomas <from+gitgub@tomr.au>
License: MIT
Project-URL: Homepage, https://github.com/rueckstiess/yanex
Project-URL: Repository, https://github.com/rueckstiess/yanex
Project-URL: Documentation, https://github.com/rueckstiess/yanex/blob/main/docs/README.md
Project-URL: Issues, https://github.com/rueckstiess/yanex/issues
Keywords: experiment,tracking,machine-learning,research,reproducibility
Classifier: Development Status :: 4 - Beta
Classifier: Intended Audience :: Developers
Classifier: Intended Audience :: Science/Research
Classifier: License :: OSI Approved :: MIT License
Classifier: Operating System :: OS Independent
Classifier: Programming Language :: Python :: 3
Classifier: Programming Language :: Python :: 3.10
Classifier: Programming Language :: Python :: 3.11
Classifier: Topic :: Scientific/Engineering
Classifier: Topic :: Software Development :: Libraries
Requires-Python: >=3.8
License-File: LICENSE
Requires-Dist: click>=8.0.0
Requires-Dist: pyyaml>=6.0
Requires-Dist: rich>=12.0.0
Requires-Dist: gitpython>=3.1.0
Requires-Dist: dateparser>=1.1.0
Requires-Dist: textual>=0.45.0
Requires-Dist: fastapi>=0.100.0
Requires-Dist: uvicorn>=0.20.0
Requires-Dist: httpx>=0.24.0
Requires-Dist: detect-secrets>=1.5.0
Requires-Dist: py-dagviz>=0.1.0
Requires-Dist: networkx>=3.0
Provides-Extra: dev
Requires-Dist: pytest>=7.0.0; extra == "dev"
Requires-Dist: pytest-cov>=4.0.0; extra == "dev"
Requires-Dist: pytest-xdist>=3.0.0; extra == "dev"
Requires-Dist: ruff>=0.1.0; extra == "dev"
Requires-Dist: mypy>=1.0.0; extra == "dev"
Provides-Extra: matplotlib
Requires-Dist: matplotlib>=3.5.0; extra == "matplotlib"
Dynamic: author
Dynamic: license-file
Dynamic: requires-python
